{"magic": "StaticPage-NetDisk=>Static Page Based File Storage System Made by htfc786 242bbd3", "create_version": "BATE0.1.0", "create_version_id": 1, "compatible_version": "BATE0.1", "compatible_version_id": 1, "name": "testnetdesk", "web_title": "\u57fa\u4e8e\u9759\u6001\u9875\u9762\u7684\u7f51\u76d8\u6d4b\u8bd5\u9875\u9762", "page_title": "\u6b22\u8fce\u8bbf\u95ee\u57fa\u4e8e\u9759\u6001\u9875\u9762\u7684\u7f51\u76d8\u6d4b\u8bd5\u9875\u9762", "little_page_title": "by--htfc786 https://github.com/htfc786/StaticPage-NetDisk/", "is_separat": true, "separate_size": 25600000}